[
  {
    "id": "level_1",
    "title": "CONSUME",
    "text": "Consume to live\nConsume to strive\nConsume to progress"
  },
  {
    "id": "level_2",
    "title": "TOOLS",
    "text": "The tools of the world are at your disposal\nUse them to fuel your consumption"
  },
  {
    "id": "level_3",
    "title": "WEED",
    "text": "Nature is but an obstacle on your path to progress"
  },
  {
    "id": "level_4",
    "title": "POWER",
    "text": "The measure of a man is what he does with power"
  },
  {
    "id": "level_5",
    "title": "Note from Spencer",
    "text": "Finally I feel great.\nEveryone is so nice to me here and I do what I love.\nDespite what they said I don't regret joining at all.\nWe will rebuild and fix everything.\nI am not going back"
  },
  {
    "id": "level_5b",
    "title": "ENTER",
    "text": "Your are but at the beginning of your journey.\nEnter and start a new tomorrow"
  }
]
